fastapi_pubsub/__init__.py
fastapi_pubsub/base.py
fastapi_pubsub/connection_manager.py
fastapi_pubsub-0.2.0.dist-info/METADATA
fastapi_pubsub-0.2.0.dist-info/WHEEL
fastapi_pubsub-0.2.0.dist-info/top_level.txt
fastapi_pubsub-0.2.0.dist-info/RECORD
